ammeter_logger/__init__.py
ammeter_logger/__main__.py
ammeter_logger/ammeter_recv.py
ammeter_logger/logging_handler.py
ammeter_logger-0.1.2.dist-info/LICENSE
ammeter_logger-0.1.2.dist-info/METADATA
ammeter_logger-0.1.2.dist-info/WHEEL
ammeter_logger-0.1.2.dist-info/top_level.txt
ammeter_logger-0.1.2.dist-info/RECORD
